devsearch/__init__.py
devsearch/__main__.py
devsearch-1.2.0.data/scripts/devsearch
devsearch-1.2.0.dist-info/LICENSE
devsearch-1.2.0.dist-info/METADATA
devsearch-1.2.0.dist-info/NOTICE
devsearch-1.2.0.dist-info/WHEEL
devsearch-1.2.0.dist-info/top_level.txt
devsearch-1.2.0.dist-info/RECORD
