Metadata-Version: 2.1
Name: devsearch
Version: 1.2.0
Summary: A project search and goto system
Home-page: http://github.com/nicmcd/devsearch
Author: Nic McDonald
Author-email: n.mcdonald83@gmail.com
License: BSD
Platform: UNKNOWN
Requires-Dist: termcolor (>=1.1.0)
